openflexure_stitching/__init__.py
openflexure_stitching/__main__.py
openflexure_stitching/correlation.py
openflexure_stitching/optimisation.py
openflexure_stitching/pipeline.py
openflexure_stitching/plotting.py
openflexure_stitching/settings.py
openflexure_stitching/types.py
openflexure_stitching/loading/__init__.py
openflexure_stitching/loading/cache.py
openflexure_stitching/loading/image.py
openflexure_stitching/loading/image_sets.py
openflexure_stitching/stitching/__init__.py
openflexure_stitching/stitching/stitch.py
openflexure_stitching/stitching/utils.py
openflexure_stitching/stitching/vips_stitch.py
openflexure_stitching/transforms/__init__.py
openflexure_stitching/transforms/affine.py
openflexure_stitching-0.2.3.dist-info/licenses/LICENSE
openflexure_stitching-0.2.3.dist-info/METADATA
openflexure_stitching-0.2.3.dist-info/WHEEL
openflexure_stitching-0.2.3.dist-info/entry_points.txt
openflexure_stitching-0.2.3.dist-info/top_level.txt
openflexure_stitching-0.2.3.dist-info/RECORD
