Metadata-Version: 2.4
Name: openflexure-stitching
Version: 0.2.3
Summary: Stitch microscopy images together into large scans.
Author-email: Joe Knapper <joe.knapper@glasgow.ac.uk>, Richard Bowman <richard.bowman@glasgow.ac.uk>, Julian Stirling <julian@julianstirling.co.uk>
License-Expression: LGPL-3.0-or-later
Project-URL: Homepage, https://gitlab.com/openflexure/openflexure-stitching
Project-URL: Bug Tracker, https://gitlab.com/openflexure/openflexure-stitching/-/issues
Classifier: Programming Language :: Python :: 3
Classifier: Operating System :: OS Independent
Requires-Python: >=3.10
License-File: LICENSE
Requires-Dist: camera-stage-mapping>=0.1.8
Requires-Dist: numpy
Requires-Dist: memory_profiler
Requires-Dist: pyvips~=3.0
Requires-Dist: piexif
Requires-Dist: pydantic~=2.10
Requires-Dist: matplotlib
Requires-Dist: psutil
Requires-Dist: scipy
Provides-Extra: libvips
Requires-Dist: pyvips-binary; extra == "libvips"
Provides-Extra: dev
Requires-Dist: pylint~=3.3; extra == "dev"
Requires-Dist: pylint_pydantic~=0.3; extra == "dev"
Requires-Dist: pylint-gitlab~=2.0; extra == "dev"
Requires-Dist: pytest~=8.3; extra == "dev"
Requires-Dist: pytest-mock==3.14; extra == "dev"
Requires-Dist: ruff~=0.11; extra == "dev"
Requires-Dist: pytest-cov~=6.1; extra == "dev"
Requires-Dist: coverage~=7.8.0; extra == "dev"
Requires-Dist: pdoc; extra == "dev"
Requires-Dist: build; extra == "dev"
Requires-Dist: twine; extra == "dev"
Requires-Dist: mypy; extra == "dev"
Requires-Dist: types-psutil; extra == "dev"
Requires-Dist: types-Pillow; extra == "dev"
Requires-Dist: scipy-stubs; extra == "dev"
Dynamic: license-file
